fastapi_logger/__init__.py
fastapi_logger/logger.py
fastapi_logger-0.2.dist-info/METADATA
fastapi_logger-0.2.dist-info/WHEEL
fastapi_logger-0.2.dist-info/top_level.txt
fastapi_logger-0.2.dist-info/RECORD
