Metadata-Version: 2.1
Name: fastapi-logger
Version: 0.2
Summary: FastAPI Logger: Enhance your FastAPI applications with comprehensive request logging.
Author: untitled69.ipynb
Author-email: ravis2114@gmail.com
Requires-Dist: fastapi
